pybose/BoseAuth.py
pybose/BoseCloudResponse.py
pybose/BoseDiscovery.py
pybose/BoseResponse.py
pybose/BoseSpeaker.py
pybose/__init__.py
pybose-2025.12.4.dist-info/licenses/LICENSE
pybose-2025.12.4.dist-info/METADATA
pybose-2025.12.4.dist-info/WHEEL
pybose-2025.12.4.dist-info/top_level.txt
pybose-2025.12.4.dist-info/RECORD
