Metadata-Version: 2.4
Name: pybose
Version: 2025.12.4
Summary: An unofficial Python API for controlling Bose soundbars and speakers.
Home-page: https://github.com/cavefire/pybose
Author: cavefire
Author-email: timo@cavefire.net
Classifier: Programming Language :: Python :: 3
Classifier: License :: OSI Approved :: GNU General Public License v3 (GPLv3)
Classifier: Operating System :: OS Independent
Requires-Python: >=3.6
License-File: LICENSE
Requires-Dist: zeroconf
Requires-Dist: websockets
Dynamic: author
Dynamic: author-email
Dynamic: classifier
Dynamic: description
Dynamic: description-content-type
Dynamic: home-page
Dynamic: license-file
Dynamic: requires-dist
Dynamic: requires-python
Dynamic: summary
